unrun/__init__.py
unrun/cli.py
unrun/utils/__init__.py
unrun/utils/config.py
unrun/utils/console.py
unrun/utils/loader.py
unrun/utils/parser.py
unrun/utils/selector.py
unrun-0.3.6.dist-info/LICENSE
unrun-0.3.6.dist-info/METADATA
unrun-0.3.6.dist-info/WHEEL
unrun-0.3.6.dist-info/entry_points.txt
unrun-0.3.6.dist-info/top_level.txt
unrun-0.3.6.dist-info/RECORD
