Metadata-Version: 2.1
Name: unrun
Version: 0.3.6
Summary: A simple CLI tool to run commands from a YAML file.
Home-page: https://github.com/howcasperwhat/unrun
Author: Casper Huang
Author-email: casper.w.huang@qq.com
License: UNKNOWN
Platform: UNKNOWN
Classifier: Programming Language :: Python :: 3
Classifier: License :: OSI Approved :: MIT License
Classifier: Operating System :: OS Independent
Requires-Python: >=3.6
License-File: LICENSE
Requires-Dist: PyYAML
Requires-Dist: rich
Requires-Dist: InquirerPy
Provides-Extra: dev
Requires-Dist: pytest-cov; extra == "dev"
Requires-Dist: pytest; extra == "dev"
Requires-Dist: flake8; extra == "dev"
Requires-Dist: twine; extra == "dev"
Requires-Dist: wheel; extra == "dev"
